bucketed_scene_flow_eval/__init__.py
bucketed_scene_flow_eval/datasets/__init__.py
bucketed_scene_flow_eval/datasets/argoverse2/__init__.py
bucketed_scene_flow_eval/datasets/argoverse2/argoverse_box_annotations.py
bucketed_scene_flow_eval/datasets/argoverse2/argoverse_raw_data.py
bucketed_scene_flow_eval/datasets/argoverse2/argoverse_scene_flow.py
bucketed_scene_flow_eval/datasets/argoverse2/av2_metacategories.py
bucketed_scene_flow_eval/datasets/argoverse2/dataset.py
bucketed_scene_flow_eval/datasets/argoverse2/symlink_camera_data.py
bucketed_scene_flow_eval/datasets/nuscenes/__init__.py
bucketed_scene_flow_eval/datasets/nuscenes/dataset.py
bucketed_scene_flow_eval/datasets/nuscenes/nuscenes_metacategories.py
bucketed_scene_flow_eval/datasets/nuscenes/nuscenes_raw_data.py
bucketed_scene_flow_eval/datasets/nuscenes/nuscenes_scene_flow.py
bucketed_scene_flow_eval/datasets/nuscenes/nuscenes_utils.py
bucketed_scene_flow_eval/datasets/orbbec_astra/__init__.py
bucketed_scene_flow_eval/datasets/orbbec_astra/dataset.py
bucketed_scene_flow_eval/datasets/waymoopen/__init__.py
bucketed_scene_flow_eval/datasets/waymoopen/dataset.py
bucketed_scene_flow_eval/datasets/waymoopen/waymo_supervised_flow.py
bucketed_scene_flow_eval/datastructures/__init__.py
bucketed_scene_flow_eval/datastructures/camera_projection.py
bucketed_scene_flow_eval/datastructures/dataclasses.py
bucketed_scene_flow_eval/datastructures/line_mesh.py
bucketed_scene_flow_eval/datastructures/o3d_visualizer.py
bucketed_scene_flow_eval/datastructures/pointcloud.py
bucketed_scene_flow_eval/datastructures/rgb_image.py
bucketed_scene_flow_eval/datastructures/se2.py
bucketed_scene_flow_eval/datastructures/se3.py
bucketed_scene_flow_eval/eval/__init__.py
bucketed_scene_flow_eval/eval/base_per_frame_sceneflow_eval.py
bucketed_scene_flow_eval/eval/bucketed_epe.py
bucketed_scene_flow_eval/eval/eval.py
bucketed_scene_flow_eval/eval/threeway_epe.py
bucketed_scene_flow_eval/interfaces/__init__.py
bucketed_scene_flow_eval-2.0.25.dist-info/METADATA
bucketed_scene_flow_eval-2.0.25.dist-info/WHEEL
bucketed_scene_flow_eval-2.0.25.dist-info/licenses/LICENSE
bucketed_scene_flow_eval-2.0.25.dist-info/RECORD
