Metadata-Version: 2.3
Name: bucketed_scene_flow_eval
Version: 2.0.25
Summary: Bucketed Scene Flow Evaluation
Author-email: Kyle Vedder <kvedder@seas.upenn.edu>
License-File: LICENSE
Classifier: License :: OSI Approved :: MIT License
Classifier: Operating System :: OS Independent
Classifier: Programming Language :: Python :: 3
Requires-Python: >=3.10
Requires-Dist: fvcore
Requires-Dist: iopath
Requires-Dist: numpy
Requires-Dist: open3d
Requires-Dist: opencv-python
Requires-Dist: pandas
Requires-Dist: pyarrow
Requires-Dist: pyquaternion
Requires-Dist: pytest
